simple_id/__init__.py
simple_id/base.py
simple_id/latex.py
simple_id/manualClassifier.py
simple_id/neuralnet.py
simple_id/occlusionMap.py
simple_id/processing_helpers.py
simple_id/training.py
simple_id/utilities.py
simple_id-0.0.4.dist-info/DESCRIPTION.rst
simple_id-0.0.4.dist-info/METADATA
simple_id-0.0.4.dist-info/RECORD
simple_id-0.0.4.dist-info/WHEEL
simple_id-0.0.4.dist-info/metadata.json
simple_id-0.0.4.dist-info/top_level.txt
